{"description":"should verify the header of the page|PaintCalculator","passed":true,"pending":false,"os":"Mac OS X","instanceId":77872,"browser":{"name":"chrome","version":"71.0.3578.98"},"message":"Passed.","trace":"","browserLogs":[{"level":"SEVERE","message":"http://127.0.0.1:5000/favicon.ico - Failed to load resource: the server responded with a status of 404 (NOT FOUND)","timestamp":1549256849261,"type":""}],"screenShotFile":"images/00ba00ab-00ed-0028-00f5-00a300c20037.png","timestamp":1549256848946,"duration":359}
